_numba_cuda_redirector.pth
_numba_cuda_redirector.py
numba_cuda/VERSION
numba_cuda/__init__.py
numba_cuda/_version.py
numba_cuda/numba/cuda/__init__.py
numba_cuda/numba/cuda/_compat.py
numba_cuda/numba/cuda/api.py
numba_cuda/numba/cuda/api_util.py
numba_cuda/numba/cuda/args.py
numba_cuda/numba/cuda/bf16.py
numba_cuda/numba/cuda/cache_hints.py
numba_cuda/numba/cuda/cg.py
numba_cuda/numba/cuda/cgutils.py
numba_cuda/numba/cuda/codegen.py
numba_cuda/numba/cuda/compiler.py
numba_cuda/numba/cuda/cuda_paths.py
numba_cuda/numba/cuda/cudadecl.py
numba_cuda/numba/cuda/cudaimpl.py
numba_cuda/numba/cuda/cudamath.py
numba_cuda/numba/cuda/debuginfo.py
numba_cuda/numba/cuda/decorators.py
numba_cuda/numba/cuda/descriptor.py
numba_cuda/numba/cuda/device_init.py
numba_cuda/numba/cuda/deviceufunc.py
numba_cuda/numba/cuda/dispatcher.py
numba_cuda/numba/cuda/errors.py
numba_cuda/numba/cuda/extending.py
numba_cuda/numba/cuda/flags.py
numba_cuda/numba/cuda/fp16.py
numba_cuda/numba/cuda/initialize.py
numba_cuda/numba/cuda/intrinsics.py
numba_cuda/numba/cuda/itanium_mangler.py
numba_cuda/numba/cuda/libdevice.py
numba_cuda/numba/cuda/libdevicedecl.py
numba_cuda/numba/cuda/libdevicefuncs.py
numba_cuda/numba/cuda/libdeviceimpl.py
numba_cuda/numba/cuda/locks.py
numba_cuda/numba/cuda/lowering.py
numba_cuda/numba/cuda/mathimpl.py
numba_cuda/numba/cuda/models.py
numba_cuda/numba/cuda/nvvmutils.py
numba_cuda/numba/cuda/printimpl.py
numba_cuda/numba/cuda/random.py
numba_cuda/numba/cuda/reshape_funcs.cu
numba_cuda/numba/cuda/serialize.py
numba_cuda/numba/cuda/simulator_init.py
numba_cuda/numba/cuda/stubs.py
numba_cuda/numba/cuda/target.py
numba_cuda/numba/cuda/testing.py
numba_cuda/numba/cuda/ufuncs.py
numba_cuda/numba/cuda/utils.py
numba_cuda/numba/cuda/vector_types.py
numba_cuda/numba/cuda/vectorizers.py
numba_cuda/numba/cuda/_internal/cuda_bf16.py
numba_cuda/numba/cuda/_internal/cuda_fp16.py
numba_cuda/numba/cuda/cext/__init__.py
numba_cuda-0.26.0.dist-info/METADATA
numba_cuda-0.26.0.dist-info/WHEEL
numba_cuda-0.26.0.dist-info/top_level.txt
numba_cuda-0.26.0.dist-info/RECORD
numba_cuda-0.26.0.dist-info/licenses/LICENSE
numba_cuda-0.26.0.dist-info/licenses/LICENSE.numba
