Metadata-Version: 2.4
Name: numba-cuda
Version: 0.26.0
Summary: CUDA target for Numba
Author: Anaconda Inc., NVIDIA Corporation
License-Expression: BSD-2-Clause
Project-URL: Homepage, https://nvidia.github.io/numba-cuda/
Project-URL: Documentation, https://nvidia.github.io/numba-cuda/
Project-URL: Repository, https://github.com/NVIDIA/numba-cuda
Project-URL: License, https://github.com/NVIDIA/numba-cuda/blob/main/LICENSE
Project-URL: Issues, https://github.com/NVIDIA/numba-cuda/issues
Requires-Python: >=3.9
License-File: LICENSE
License-File: LICENSE.numba
Requires-Dist: numba>=0.60.0
Requires-Dist: cuda-bindings<14.0.0,>=12.9.1
Requires-Dist: cuda-core<1.0.0,>=0.5.1
Requires-Dist: packaging
Provides-Extra: cu12
Requires-Dist: cuda-bindings<13.0.0,>=12.9.1; extra == "cu12"
Requires-Dist: cuda-pathfinder<2.0.0,>=1.3.1; extra == "cu12"
Requires-Dist: cuda-toolkit[cccl,cudart,nvcc,nvjitlink,nvrtc]==12.*; extra == "cu12"
Provides-Extra: cu13
Requires-Dist: cuda-bindings==13.*; extra == "cu13"
Requires-Dist: cuda-pathfinder<2.0.0,>=1.3.1; extra == "cu13"
Requires-Dist: cuda-toolkit[cccl,cudart,nvjitlink,nvrtc,nvvm]==13.*; extra == "cu13"
Dynamic: license-file
